akttym/__init__.py
akttym/__main__.py
akttym/akttym.py
akttym/config.yaml
akttym-0.1.4.dist-info/DESCRIPTION.rst
akttym-0.1.4.dist-info/METADATA
akttym-0.1.4.dist-info/RECORD
akttym-0.1.4.dist-info/WHEEL
akttym-0.1.4.dist-info/dependency_links.txt
akttym-0.1.4.dist-info/entry_points.txt
akttym-0.1.4.dist-info/metadata.json
akttym-0.1.4.dist-info/top_level.txt
