Metadata-Version: 2.0
Name: akttym
Version: 0.1.4
Summary: Add currently plaing track by Spotify to your music library, headlessly
Home-page: UNKNOWN
Author: UNKNOWN
Author-email: UNKNOWN
License: UNKNOWN
Platform: UNKNOWN
Requires-Dist: pyyaml
Requires-Dist: spotipy
